README.md
setup.py
rwm/__init__.py
rwm/database.py
rwm/handlers.py
rwm/hooks.py
rwm/routes.py
rwm.egg-info/PKG-INFO
rwm.egg-info/SOURCES.txt
rwm.egg-info/dependency_links.txt
rwm.egg-info/top_level.txt